{
  "objectInfo" : {
    "id" : "ajxFaCK5JCZlNYIoSztQmD",
    "name" : "Parse_Versioning_Dict_21",
    "type" : "PARSE",
    "metadata" : {
      "modelVersion" : {
        "major" : 1,
        "minor" : 0
      },
      "repoInfo" : {
        "repoHandle" : "ajxFaCK5JCZlNYIoSztQmD"
      },
      "contextAttributes" : [ ],
      "additionalInfo" : {
        "description" : "d",
        "contentType" : "Binary",
        "documentState" : "VALID"
      }
    }
  },
  "dataFileExtension" : "json",
  "objectRefs" : [ {
    "id" : "15775uGOzg8kpftlgDebsq",
    "name" : "Dictionary2_Project_Versioning_2",
    "type" : "DICTIONARY",
    "metadata" : {
      "modelVersion" : {
        "major" : 1,
        "minor" : 0
      },
      "repoInfo" : {
        "repoHandle" : "15775uGOzg8kpftlgDebsq"
      },
      "contextAttributes" : null,
      "additionalInfo" : {
        "description" : "example&&&!!!!",
        "contentType" : "Binary",
        "documentState" : "VALID"
      }
    },
    "path" : "/Explore/Auto_Project_Git_Version_2"
  } ]
}