{
  "objectInfo" : {
    "id" : "ecuvmvl56IccFxdgWrr2Aq",
    "name" : "Profile_CH",
    "type" : "PROFILE",
    "metadata" : {
      "modelVersion" : {
        "major" : 1,
        "minor" : 0
      },
      "repoInfo" : {
        "repoHandle" : "d961bf0f-0e7a-453b-9558-2d7266a3ec7e"
      },
      "contextAttributes" : [ ],
      "additionalInfo" : {
        "description" : null,
        "contentType" : "Binary",
        "documentState" : "COMPLETE"
      }
    }
  },
  "dataFileExtension" : "json",
  "objectRefs" : [ {
    "id" : "dDMdEKuTcaPhYT4CHEt26N",
    "name" : "ORA_SRC",
    "type" : "Connection",
    "metadata" : {
      "modelVersion" : {
        "major" : 0,
        "minor" : 0
      },
      "repoInfo" : {
        "repoHandle" : "0100420B000000000009"
      },
      "contextAttributes" : null,
      "additionalInfo" : {
        "description" : null,
        "contentType" : "JSON",
        "documentState" : "COMPLETE"
      }
    },
    "path" : "/SYS"
  } ]
}