{
  "objectInfo" : {
    "id" : "4TVBWN2hMt3hlJrC45fLKT",
    "name" : "Parse_Versioning_2",
    "type" : "PARSE",
    "metadata" : {
      "modelVersion" : {
        "major" : 1,
        "minor" : 0
      },
      "repoInfo" : {
        "repoHandle" : "4TVBWN2hMt3hlJrC45fLKT"
      },
      "contextAttributes" : [ ],
      "additionalInfo" : {
        "description" : null,
        "contentType" : "Binary",
        "documentState" : "VALID"
      }
    }
  },
  "dataFileExtension" : "json",
  "objectRefs" : [ ]
}