{"doc":{"id":"3Gz4xGTsoI2jAPy57SGfSW","name":"Dictionary1215","description":null,"documentType":"DICTIONARY","repoInfo":{"repoPath":"","repoHandle":"3Gz4xGTsoI2jAPy57SGfSW"},"docRef":null,"customAttributes":{"stringAttrs":[]},"nativeData":{"id":"3Gz4xGTsoI2jAPy57SGfSW","documentBlob":"{\"name\":\"\",\"defaultValueLiteral\":\"\",\"description\":\"\",\"readRelationalDSO\":{\"relationalFields\":[{\"name\":\"Column 1\",\"odbcPrecision\":512,\"label\":\"Column 1\"},{\"name\":\"Column 2\",\"odbcPrecision\":512,\"label\":\"Column 2\"}]},\"tags\": []}"}},"data":"{\"rows\":[[0,\"INFA\",\"DQ\"],[1,\"TESTING\",\"PROJECT\"]],\"cols\":[\"unique_row_identifier\",\"Column 1\",\"Column 2\"]}"}