{
  "objectInfo" : {
    "id" : "1DCKryQyOI1cCrt2M9w5o6",
    "name" : "Deduplication_Versioning_2",
    "type" : "DEDUPLICATE",
    "metadata" : {
      "modelVersion" : {
        "major" : 1,
        "minor" : 0
      },
      "repoInfo" : {
        "repoHandle" : "1DCKryQyOI1cCrt2M9w5o6"
      },
      "contextAttributes" : [ ],
      "additionalInfo" : {
        "description" : null,
        "contentType" : "Binary",
        "documentState" : "VALID"
      }
    }
  },
  "dataFileExtension" : "json",
  "objectRefs" : [ ]
}