{
  "objectInfo" : {
    "id" : "3s5F2UpD3qJe93ySxaWHCI",
    "name" : "Dictionary1_Project_Versioning",
    "type" : "DICTIONARY",
    "metadata" : {
      "modelVersion" : {
        "major" : 1,
        "minor" : 0
      },
      "repoInfo" : {
        "repoHandle" : "3s5F2UpD3qJe93ySxaWHCI"
      },
      "contextAttributes" : [ ],
      "additionalInfo" : {
        "description" : null,
        "contentType" : "Binary",
        "documentState" : "VALID"
      }
    }
  },
  "dataFileExtension" : "json",
  "objectRefs" : [ ]
}